<config>
	<site>http://zzadmin:sharezzphotos@share1001photos.zangzing.com/</site>
	<test_module name="login">
		<login_html_id>user_session_email</login_html_id>
		<passwd_html_id>user_session_password</passwd_html_id>
		<send_html_id>//a[@id='signin-form-submit-button']/span</send_html_id>
	</test_module>
	<test_module name="search">
                <search_html_id>searchlogID</search_html_id>
                <send_html_id>SearchbuttonID</send_html_id>
        </test_module>
	<test_module name="reg">
		<reg_name_id>user_name</reg_name_id>
		<reg_login_id>user_username</reg_login_id>
		<reg_email_id>user_email</reg_email_id>
		<reg_pass_id>user_password</reg_pass_id>
		<reg_confirm_id>submit</reg_confirm_id>
	</test_module>
</config>
